MANIFEST.in
README.txt
setup.cfg
setup.py
atrealtheme/__init__.py
atrealtheme/__init__.pyc
atrealtheme.algol.egg-info/PKG-INFO
atrealtheme.algol.egg-info/SOURCES.txt
atrealtheme.algol.egg-info/dependency_links.txt
atrealtheme.algol.egg-info/entry_points.txt
atrealtheme.algol.egg-info/namespace_packages.txt
atrealtheme.algol.egg-info/not-zip-safe
atrealtheme.algol.egg-info/paster_plugins.txt
atrealtheme.algol.egg-info/requires.txt
atrealtheme.algol.egg-info/top_level.txt
atrealtheme/algol/__init__.py
atrealtheme/algol/configure.zcml
atrealtheme/algol/profiles.zcml
atrealtheme/algol/setuphandlers.py
atrealtheme/algol/skins.zcml
atrealtheme/algol/tests.py
atrealtheme/algol/version.txt
atrealtheme/algol/browser/__init__.py
atrealtheme/algol/browser/__init__.pyc
atrealtheme/algol/browser/configure.zcml
atrealtheme/algol/browser/footer.pt
atrealtheme/algol/browser/interfaces.py
atrealtheme/algol/browser/interfaces.pyc
atrealtheme/algol/browser/search_portlet.pt
atrealtheme/algol/browser/viewlet.pt
atrealtheme/algol/browser/viewlets.py
atrealtheme/algol/browser/images/README.txt
atrealtheme/algol/browser/stylesheets/README.txt
atrealtheme/algol/browser/stylesheets/main.css
atrealtheme/algol/profiles/default/atrealtheme.algol_various.txt
atrealtheme/algol/profiles/default/cssregistry.xml
atrealtheme/algol/profiles/default/import_steps.xml
atrealtheme/algol/profiles/default/jsregistry.xml
atrealtheme/algol/profiles/default/metadata.xml
atrealtheme/algol/profiles/default/skins.xml
atrealtheme/algol/profiles/default/viewlets.xml
atrealtheme/algol/skins/atrealtheme_algol_custom_images/CONTENT.txt
atrealtheme/algol/skins/atrealtheme_algol_custom_images/bg-content.jpg
atrealtheme/algol/skins/atrealtheme_algol_custom_images/bg-li-menu.jpg
atrealtheme/algol/skins/atrealtheme_algol_custom_images/bg-site.jpg
atrealtheme/algol/skins/atrealtheme_algol_custom_images/bg-site2.jpg
atrealtheme/algol/skins/atrealtheme_algol_custom_images/deco.jpg
atrealtheme/algol/skins/atrealtheme_algol_custom_images/footer.jpg
atrealtheme/algol/skins/atrealtheme_algol_custom_images/header.jpg
atrealtheme/algol/skins/atrealtheme_algol_custom_images/header2.jpg
atrealtheme/algol/skins/atrealtheme_algol_custom_images/plone-logo-64.jpg
atrealtheme/algol/skins/atrealtheme_algol_custom_images/side-h2.jpg
atrealtheme/algol/skins/atrealtheme_algol_custom_templates/CONTENT.txt
