Metadata-Version: 1.0
Name: atrealtheme.algol
Version: 1.0.0beta1
Summary: An installable theme for Plone 3.0
Home-page: http://www.atreal.net/
Author: atReal
Author-email: contact@atreal.net
License: GPL
Keywords: web zope plone theme
Platform: UNKNOWN
Classifier: Framework :: Plone
Classifier: Programming Language :: Python
Classifier: Topic :: Software Development :: Libraries :: Python Modules
